mypy_typing_asserts/__init__.py
mypy_typing_asserts/mypy_plugin.py
mypy_typing_asserts/py.typed
mypy_typing_asserts-0.1.1.dist-info/LICENSE
mypy_typing_asserts-0.1.1.dist-info/WHEEL
mypy_typing_asserts-0.1.1.dist-info/METADATA
mypy_typing_asserts-0.1.1.dist-info/RECORD
