Metadata-Version: 2.1
Name: mypy-typing-asserts
Version: 0.1.1
Summary: Adds the ability to _assert_ types when typechecking to mypy
Home-page: https://github.com/thejcannon/mypy-typing-asserts
Keywords: mypy
Author: Joshua Cannon
Author-email: joshdcannon@gmail.com
Requires-Python: >=3.7,<4.0
Classifier: Programming Language :: Python :: 3
Classifier: Programming Language :: Python :: 3.10
Classifier: Programming Language :: Python :: 3.7
Classifier: Programming Language :: Python :: 3.8
Classifier: Programming Language :: Python :: 3.9
Classifier: Typing :: Typed
Project-URL: Repository, https://github.com/thejcannon/mypy-typing-asserts
